vodozemac-0.9.0.post1.dist-info/METADATA
vodozemac-0.9.0.post1.dist-info/WHEEL
vodozemac-0.9.0.post1.dist-info/licenses/LICENSE
vodozemac/__init__.py
vodozemac/__init__.pyi
vodozemac/py.typed
vodozemac/vodozemac.cpython-313-darwin.so
vodozemac-0.9.0.post1.dist-info/RECORD
