Metadata-Version: 2.4
Name: vodozemac
Version: 0.9.0.post1
Classifier: Programming Language :: Python :: 3 :: Only
Classifier: Programming Language :: Python :: 3.9
Classifier: Programming Language :: Python :: 3.10
Classifier: Programming Language :: Python :: 3.11
Classifier: Programming Language :: Python :: 3.12
Classifier: Programming Language :: Python :: 3.13
License-File: LICENSE
Summary: Python bindings for vodozemac
Home-Page: https://github.com/matrix-nio/vodozemac-python
Requires-Python: >=3.9
Project-URL: repository, https://github.com/matrix-nio/vodozemac-python
